servents/data_model/__init__.py
servents/data_model/derived_consts.py
servents/data_model/entity_configs.py
servents/data_model/entity_types.py
servents/data_model/update_entity.py
servents_data_model-0.6.0.dist-info/METADATA
servents_data_model-0.6.0.dist-info/WHEEL
servents_data_model-0.6.0.dist-info/top_level.txt
servents_data_model-0.6.0.dist-info/RECORD
