Metadata-Version: 2.4
Name: servents-data-model
Version: 0.6.0
Summary: Servents is a custom_component for home assistant to allow creation and tracking of entities programatically
Author-email: Carlos Sarmiento <carlos5678@gmail.com>
Requires-Python: >=3.13.2
Requires-Dist: pyserde>=0.23.0
